helloeverything/__init__.py
helloeverthing-0.1.dist-info/METADATA
helloeverthing-0.1.dist-info/WHEEL
helloeverthing-0.1.dist-info/top_level.txt
helloeverthing-0.1.dist-info/RECORD
