Metadata-Version: 2.1
Name: helloeverthing
Version: 0.1
Summary: Simple library for random generations
Home-page: https://github.com/Dron3916/helloworld
Author: Rodionov Andrew
Author-email: dron3915work@gmail.com
License: UNKNOWN
Platform: UNKNOWN
Classifier: Programming Language :: Python :: 3
Classifier: License :: OSI Approved :: MIT License
Classifier: Operating System :: OS Independent
Requires-Python: >=3
